[
  {
    "id": "Beaches_promenade_beach",
    "category": "Beaches",
    "subCategory": "Beach",
    "name": "Promenade Beach",
    "location": "White Town",
    "address": "White Town",
    "googleMapsUrl": "https://maps.google.com/?q=Promenade+Beach+Puducherry",
    "openingTimeWeekdays": "24x7",
    "closingTimeWeekdays": "Not specified",
    "openingTimeWeekends": "24x7",
    "closingTimeWeekends": "Not specified",
    "description": "Historic French-era beachfront",
    "images": [],
    "entryFee": "Free",
    "dressCode": "Not specified",
    "phoneNumber": "Tourism Dept",
    "crowdLevel": "High",
    "bestTimeToVisit": "Early morning, Evening",
    "famousFor": "Sunrise / Sunset point (No swimming)",
    "safetyNotes": "High safety, Police patrol",
    "lastVerified": "2026-02-07T17:21:58.550Z"
  },
  {
    "id": "Beaches_paradise_beach",
    "category": "Beaches",
    "subCategory": "Beach",
    "name": "Paradise Beach",
    "location": "Chunnambar",
    "address": "Chunnambar",
    "googleMapsUrl": "https://maps.google.com/?q=Paradise+Beach+Puducherry",
    "openingTimeWeekdays": "8:00 AM",
    "closingTimeWeekdays": "5:00 PM",
    "openingTimeWeekends": "8:00 AM",
    "closingTimeWeekends": "5:00 PM",
    "description": "Accessible only by boat",
    "images": [],
    "entryFee": "Boat fee applicable",
    "dressCode": "Not specified",
    "phoneNumber": "Tourism Dept",
    "crowdLevel": "High",
    "bestTimeToVisit": "Morning",
    "famousFor": "Swimming allowed",
    "safetyNotes": "Moderate safety, Lifeguards available",
    "lastVerified": "2026-02-07T17:21:58.550Z"
  },
  {
    "id": "Beaches_serenity_beach",
    "category": "Beaches",
    "subCategory": "Beach",
    "name": "Serenity Beach",
    "location": "Kottakuppam",
    "address": "Kottakuppam",
    "googleMapsUrl": "https://maps.google.com/?q=Serenity+Beach+Puducherry",
    "openingTimeWeekdays": "5:00 AM",
    "closingTimeWeekdays": "8:00 PM",
    "openingTimeWeekends": "5:00 AM",
    "closingTimeWeekends": "8:00 PM",
    "description": "Popular among surfers",
    "images": [],
    "entryFee": "Free",
    "dressCode": "Not specified",
    "phoneNumber": "Local Panchayat",
    "crowdLevel": "Medium",
    "bestTimeToVisit": "Morning",
    "famousFor": "Surfing, Swimming (with caution)",
    "safetyNotes": "Moderate safety, Lifeguards limited",
    "lastVerified": "2026-02-07T17:21:58.550Z"
  },
  {
    "id": "Beaches_auroville_beach",
    "category": "Beaches",
    "subCategory": "Beach",
    "name": "Auroville Beach",
    "location": "Auroville",
    "address": "Auroville",
    "googleMapsUrl": "https://maps.google.com/?q=Auroville+Beach",
    "openingTimeWeekdays": "5:00 AM",
    "closingTimeWeekdays": "7:00 PM",
    "openingTimeWeekends": "5:00 AM",
    "closingTimeWeekends": "7:00 PM",
    "description": "Rocky shoreline",
    "images": [],
    "entryFee": "Free",
    "dressCode": "Not specified",
    "phoneNumber": "Local authority",
    "crowdLevel": "Low",
    "bestTimeToVisit": "Morning",
    "famousFor": "Swimming not advised",
    "safetyNotes": "Low safety, No lifeguards",
    "lastVerified": "2026-02-07T17:21:58.550Z"
  },
  {
    "id": "Beaches_reppo_beach",
    "category": "Beaches",
    "subCategory": "Beach",
    "name": "Reppo Beach",
    "location": "Kalapet",
    "address": "Kalapet",
    "googleMapsUrl": "https://maps.google.com/?q=Reppo+Beach+Puducherry",
    "openingTimeWeekdays": "6:00 AM",
    "closingTimeWeekdays": "6:00 PM",
    "openingTimeWeekends": "6:00 AM",
    "closingTimeWeekends": "6:00 PM",
    "description": "Quiet and less crowded",
    "images": [],
    "entryFee": "Free",
    "dressCode": "Not specified",
    "phoneNumber": "Local Panchayat",
    "crowdLevel": "Low",
    "bestTimeToVisit": "Evening",
    "famousFor": "Sunset point",
    "safetyNotes": "Low safety, No lifeguards",
    "lastVerified": "2026-02-07T17:21:58.550Z"
  },
  {
    "id": "Beaches_veerampattinam_beach",
    "category": "Beaches",
    "subCategory": "Beach",
    "name": "Veerampattinam Beach",
    "location": "Veerampattinam",
    "address": "Veerampattinam",
    "googleMapsUrl": "https://maps.google.com/?q=Veerampattinam+Beach",
    "openingTimeWeekdays": "6:00 AM",
    "closingTimeWeekdays": "6:00 PM",
    "openingTimeWeekends": "6:00 AM",
    "closingTimeWeekends": "6:00 PM",
    "description": "Famous fishing village",
    "images": [],
    "entryFee": "Free",
    "dressCode": "Not specified",
    "phoneNumber": "Village Council",
    "crowdLevel": "Medium",
    "bestTimeToVisit": "Morning",
    "famousFor": "Fishing village beach",
    "safetyNotes": "Low safety, No lifeguards",
    "lastVerified": "2026-02-07T17:21:58.550Z"
  },
  {
    "id": "Beaches_chunnambar_backwater",
    "category": "Beaches",
    "subCategory": "Beach",
    "name": "Chunnambar Backwater",
    "location": "Chunnambar",
    "address": "Chunnambar",
    "googleMapsUrl": "https://maps.google.com/?q=Chunnambar+Backwater",
    "openingTimeWeekdays": "9:00 AM",
    "closingTimeWeekdays": "5:00 PM",
    "openingTimeWeekends": "9:00 AM",
    "closingTimeWeekends": "5:00 PM",
    "description": "Backwater boating point",
    "images": [],
    "entryFee": "Paid",
    "dressCode": "Not specified",
    "phoneNumber": "Tourism Dept",
    "crowdLevel": "Medium",
    "bestTimeToVisit": "Morning",
    "famousFor": "Backwater recreation",
    "safetyNotes": "High safety, Staff present",
    "lastVerified": "2026-02-07T17:21:58.550Z"
  },
  {
    "id": "Beaches_quiet_healing_centre_beach",
    "category": "Beaches",
    "subCategory": "Beach",
    "name": "Quiet Healing Centre Beach",
    "location": "Auroville",
    "address": "Auroville",
    "googleMapsUrl": "https://maps.google.com/?q=Quiet+Healing+Centre+Beach",
    "openingTimeWeekdays": "5:00 AM",
    "closingTimeWeekdays": "6:00 PM",
    "openingTimeWeekends": "5:00 AM",
    "closingTimeWeekends": "6:00 PM",
    "description": "Spiritual calm zone",
    "images": [],
    "entryFee": "Free",
    "dressCode": "Not specified",
    "phoneNumber": "Local authority",
    "crowdLevel": "Low",
    "bestTimeToVisit": "Morning",
    "famousFor": "Meditation, Quiet beach",
    "safetyNotes": "Low safety",
    "lastVerified": "2026-02-07T17:21:58.550Z"
  }
]