[
  {
    "id": "Restraunts_villa_shanti",
    "category": "Restraunts",
    "subCategory": "Casual Dining",
    "name": "Villa Shanti",
    "location": "White Town",
    "address": "White Town",
    "googleMapsUrl": "https://maps.google.com/?q=Villa+Shanti+Puducherry",
    "openingTimeWeekdays": "12:00 PM",
    "closingTimeWeekdays": "10:30 PM",
    "openingTimeWeekends": "12:00 PM",
    "closingTimeWeekends": "10:30 PM",
    "description": "Heritage restaurant",
    "images": [],
    "entryFee": "800-1500",
    "dressCode": "Not specified",
    "phoneNumber": "4134200028",
    "crowdLevel": "Medium",
    "bestTimeToVisit": "All year",
    "famousFor": "",
    "safetyNotes": "",
    "lastVerified": "2026-02-07T17:21:58.552Z"
  },
  {
    "id": "Restraunts_theevu_plage",
    "category": "Restraunts",
    "subCategory": "Fine Dining",
    "name": "Theevu Plage",
    "location": "Kottakuppam",
    "address": "Kottakuppam",
    "googleMapsUrl": "https://maps.google.com/?q=Theevu+Plage",
    "openingTimeWeekdays": "12:30 PM",
    "closingTimeWeekdays": "10:00 PM",
    "openingTimeWeekends": "12:30 PM",
    "closingTimeWeekends": "10:00 PM",
    "description": "Beachside dining",
    "images": [],
    "entryFee": "1200-2000",
    "dressCode": "Not specified",
    "phoneNumber": "9600777038",
    "crowdLevel": "Medium",
    "bestTimeToVisit": "All year",
    "famousFor": "",
    "safetyNotes": "",
    "lastVerified": "2026-02-07T17:21:58.552Z"
  },
  {
    "id": "Restraunts_coromandel_cafe",
    "category": "Restraunts",
    "subCategory": "Hotel Dining",
    "name": "Coromandel Cafe",
    "location": "White Town",
    "address": "White Town",
    "googleMapsUrl": "https://maps.google.com/?q=Coromandel+Cafe+Puducherry",
    "openingTimeWeekdays": "7:00 AM",
    "closingTimeWeekdays": "10:30 PM",
    "openingTimeWeekends": "7:00 AM",
    "closingTimeWeekends": "10:30 PM",
    "description": "Hotel restaurant",
    "images": [],
    "entryFee": "900-1800",
    "dressCode": "Not specified",
    "phoneNumber": "9489214332",
    "crowdLevel": "Medium",
    "bestTimeToVisit": "All year",
    "famousFor": "",
    "safetyNotes": "",
    "lastVerified": "2026-02-07T17:21:58.553Z"
  },
  {
    "id": "Restraunts_cafe_des_arts",
    "category": "Restraunts",
    "subCategory": "French",
    "name": "Cafe des Arts",
    "location": "White Town",
    "address": "White Town",
    "googleMapsUrl": "https://maps.google.com/?q=Cafe+des+Arts",
    "openingTimeWeekdays": "8:30 AM",
    "closingTimeWeekdays": "10 PM",
    "openingTimeWeekends": "8:30 AM",
    "closingTimeWeekends": "10 PM",
    "description": "Artistic cafe",
    "images": [
      "https://maps.app.goo.gl/h6NaA6yYzmnfcztLA"
    ],
    "entryFee": "300-700",
    "dressCode": "Not specified",
    "phoneNumber": "81221 30066",
    "crowdLevel": "Medium",
    "bestTimeToVisit": "All year",
    "famousFor": "Croissants",
    "safetyNotes": "",
    "lastVerified": "2026-02-07T17:21:58.553Z"
  },
  {
    "id": "Restraunts_bread_chocolate",
    "category": "Restraunts",
    "subCategory": "Bakery Cafe",
    "name": "Bread & Chocolate",
    "location": "MG Road",
    "address": "MG Road",
    "googleMapsUrl": "https://maps.google.com/?q=Bread+and+Chocolate",
    "openingTimeWeekdays": "9 AM",
    "closingTimeWeekdays": "9 PM",
    "openingTimeWeekends": "9 AM",
    "closingTimeWeekends": "9 PM",
    "description": "Cozy cafe",
    "images": [
      "https://maps.app.goo.gl/7shg2zJBvYYxcptW9"
    ],
    "entryFee": "250-600",
    "dressCode": "Not specified",
    "phoneNumber": "8940058500",
    "crowdLevel": "Medium",
    "bestTimeToVisit": "All year",
    "famousFor": "Chocolate Tart",
    "safetyNotes": "",
    "lastVerified": "2026-02-07T17:21:58.553Z"
  },
  {
    "id": "Restraunts_zuka_choco_la",
    "category": "Restraunts",
    "subCategory": "Dessert Cafe",
    "name": "Zuka Choco-la",
    "location": "White Town",
    "address": "White Town",
    "googleMapsUrl": "https://maps.google.com/?q=Zuka+Chocolates",
    "openingTimeWeekdays": "10 AM",
    "closingTimeWeekdays": "9 PM",
    "openingTimeWeekends": "10 AM",
    "closingTimeWeekends": "9 PM",
    "description": "Chocolate specialty",
    "images": [
      "https://maps.app.goo.gl/A3pSvmbAEYJ4KUHY7"
    ],
    "entryFee": "300-800",
    "dressCode": "Not specified",
    "phoneNumber": "4132221191",
    "crowdLevel": "Medium",
    "bestTimeToVisit": "All year",
    "famousFor": "Hot Chocolate",
    "safetyNotes": "",
    "lastVerified": "2026-02-07T17:21:58.553Z"
  },
  {
    "id": "Restraunts_hot_breads",
    "category": "Restraunts",
    "subCategory": "Bakeries_Snack_Desserts",
    "name": "Hot Breads",
    "location": "MG Road",
    "address": "MG Road",
    "googleMapsUrl": "https://maps.google.com/?q=Hot+Breads+Puducherry",
    "openingTimeWeekdays": "Not specified",
    "closingTimeWeekdays": "Not specified",
    "openingTimeWeekends": "Not specified",
    "closingTimeWeekends": "Not specified",
    "description": "Popular bakery",
    "images": [
      "https://maps.app.goo.gl/Tderr2grrR4fPACn7"
    ],
    "entryFee": "50-200",
    "dressCode": "Not specified",
    "phoneNumber": "9566079526",
    "crowdLevel": "Medium",
    "bestTimeToVisit": "All year",
    "famousFor": "Pastries",
    "safetyNotes": "",
    "lastVerified": "2026-02-07T17:21:58.553Z"
  },
  {
    "id": "Restraunts_baker_street",
    "category": "Restraunts",
    "subCategory": "Bakeries_Snack_Desserts",
    "name": "Baker Street",
    "location": "MG Road",
    "address": "MG Road",
    "googleMapsUrl": "https://maps.google.com/?q=Baker+Street+Puducherry",
    "openingTimeWeekdays": "Not specified",
    "closingTimeWeekdays": "Not specified",
    "openingTimeWeekends": "Not specified",
    "closingTimeWeekends": "Not specified",
    "description": "French bakery",
    "images": [
      "https://maps.app.goo.gl/uAwXTS1GnyyCLsCz5"
    ],
    "entryFee": "80-250",
    "dressCode": "Not specified",
    "phoneNumber": "9944850001",
    "crowdLevel": "Medium",
    "bestTimeToVisit": "All year",
    "famousFor": "Brownies",
    "safetyNotes": "",
    "lastVerified": "2026-02-07T17:21:58.553Z"
  },
  {
    "id": "Restraunts_ashok_chaat",
    "category": "Restraunts",
    "subCategory": "Chats",
    "name": "Ashok Chaat",
    "location": "Mission Street",
    "address": "Mission Street",
    "googleMapsUrl": "https://maps.google.com/?q=Ashok+Chaat",
    "openingTimeWeekdays": "4 PM",
    "closingTimeWeekdays": "Not specified",
    "openingTimeWeekends": "4 PM",
    "closingTimeWeekends": "Not specified",
    "description": "Famous chaat stall",
    "images": [],
    "entryFee": "Low",
    "dressCode": "Not specified",
    "phoneNumber": "",
    "crowdLevel": "Medium",
    "bestTimeToVisit": "All year",
    "famousFor": "Pani Puri",
    "safetyNotes": "",
    "lastVerified": "2026-02-07T17:21:58.553Z"
  },
  {
    "id": "Restraunts_balaji_chaat",
    "category": "Restraunts",
    "subCategory": "Chats",
    "name": "Balaji Chaat",
    "location": "Lawspet",
    "address": "Lawspet",
    "googleMapsUrl": "https://maps.google.com/?q=Balaji+Chaat+Puducherry",
    "openingTimeWeekdays": "5 PM",
    "closingTimeWeekdays": "Not specified",
    "openingTimeWeekends": "5 PM",
    "closingTimeWeekends": "Not specified",
    "description": "Local favorite",
    "images": [],
    "entryFee": "Low",
    "dressCode": "Not specified",
    "phoneNumber": "",
    "crowdLevel": "Medium",
    "bestTimeToVisit": "All year",
    "famousFor": "Dahi Puri",
    "safetyNotes": "",
    "lastVerified": "2026-02-07T17:21:58.553Z"
  },
  {
    "id": "Restraunts_gupta_chaat",
    "category": "Restraunts",
    "subCategory": "Chats",
    "name": "Gupta Chaat",
    "location": "MG Road",
    "address": "MG Road",
    "googleMapsUrl": "https://maps.google.com/?q=Gupta+Chaat+Puducherry",
    "openingTimeWeekdays": "4:30 PM",
    "closingTimeWeekdays": "Not specified",
    "openingTimeWeekends": "4:30 PM",
    "closingTimeWeekends": "Not specified",
    "description": "Budget chaat",
    "images": [],
    "entryFee": "Low",
    "dressCode": "Not specified",
    "phoneNumber": "",
    "crowdLevel": "Medium",
    "bestTimeToVisit": "All year",
    "famousFor": "Bhel Puri",
    "safetyNotes": "",
    "lastVerified": "2026-02-07T17:21:58.553Z"
  },
  {
    "id": "Restraunts_rock_beach_stalls",
    "category": "Restraunts",
    "subCategory": "Snacks",
    "name": "Rock Beach Stalls",
    "location": "Promenade",
    "address": "Promenade",
    "googleMapsUrl": "https://maps.google.com/?q=Rock+Beach",
    "openingTimeWeekdays": "Not specified",
    "closingTimeWeekdays": "Not specified",
    "openingTimeWeekends": "Not specified",
    "closingTimeWeekends": "Not specified",
    "description": "Evening food hub",
    "images": [],
    "entryFee": "20-80",
    "dressCode": "Not specified",
    "phoneNumber": "",
    "crowdLevel": "Medium",
    "bestTimeToVisit": "All year",
    "famousFor": "Bajji, Corn",
    "safetyNotes": "",
    "lastVerified": "2026-02-07T17:21:58.553Z"
  },
  {
    "id": "Restraunts_sunday_market_food",
    "category": "Restraunts",
    "subCategory": "Mixed",
    "name": "Sunday Market Food",
    "location": "Heritage Town",
    "address": "Heritage Town",
    "googleMapsUrl": "https://maps.google.com/?q=Sunday+Market+Puducherry",
    "openingTimeWeekdays": "Not specified",
    "closingTimeWeekdays": "Not specified",
    "openingTimeWeekends": "Not specified",
    "closingTimeWeekends": "Not specified",
    "description": "Weekend food stalls",
    "images": [],
    "entryFee": "50-120",
    "dressCode": "Not specified",
    "phoneNumber": "",
    "crowdLevel": "Medium",
    "bestTimeToVisit": "All year",
    "famousFor": "Fried Rice",
    "safetyNotes": "",
    "lastVerified": "2026-02-07T17:21:58.553Z"
  },
  {
    "id": "Restraunts_lawspet_evening_stalls",
    "category": "Restraunts",
    "subCategory": "Snacks",
    "name": "Lawspet Evening Stalls",
    "location": "Lawspet",
    "address": "Lawspet",
    "googleMapsUrl": "https://maps.google.com/?q=Lawspet+Street+Food",
    "openingTimeWeekdays": "Not specified",
    "closingTimeWeekdays": "Not specified",
    "openingTimeWeekends": "Not specified",
    "closingTimeWeekends": "Not specified",
    "description": "Local snack stalls",
    "images": [],
    "entryFee": "20-60",
    "dressCode": "Not specified",
    "phoneNumber": "",
    "crowdLevel": "Medium",
    "bestTimeToVisit": "All year",
    "famousFor": "Vada,Bajji",
    "safetyNotes": "",
    "lastVerified": "2026-02-07T17:21:58.553Z"
  }
]